Workbook
Name Slicer_Gender_Category: #N/A
Name Slicer_Product_Line: #N/A
Name Slicer_Region: #N/A
Name Slicer_Sales_Channel: #N/A

Sheet Nike_Sales_Uncleaned
A1: Order_ID | B1: Gender_Category | C1: Product_Line | D1: Product_Name | E1: Size | F1: Units_Sold | G1: MRP | H1: Discount_Applied | I1: Revenue | J1: Order_Date | K1: Sales_Channel | L1: Region | M1: Profit
A2: 2016 | B2: Women | C2: Basketball | D2: Air Jordan | E2: M | F2: 1 | G2: 9871.75 | H2: 0.3 | I2: 6910.22 | K2: Retail | L2: Hyderabad | M2: 2452.69
A3: 2031 | B3: Men | C3: Soccer | D3: Premier Iii | F3: 4 | G3: 3493.04 | H3: 0.82 | I3: 2514.99 | J3: 45421 | K3: Online | L3: Delhi | M3: 350.7
A4: 2063 | B4: Women | C4: Basketball | D4: Air Jordan | E4: M | F4: 1 | G4: 9751 | H4: 0.16 | I4: 8190.84 | J4: 45541 | K4: Retail | L4: Pune | M4: 1130.31
A5: 2071 | B5: Kids | C5: Lifestyle | D5: Blazer Mid | E5: M | F5: 3 | G5: 7849.81 | H5: 0.49 | I5: 12010.21 | J5: 45669 | K5: Retail | L5: Pune | M5: -882.96
A6: 2089 | B6: Women | C6: Training | D6: Flex Trainer | E6: L | F6: 2 | G6: 6874.77 | H6: 0.6 | I6: 5499.82 | J6: 45628 | K6: Online | L6: Mumbai | M6: -1076.66
A7: 2114 | B7: Women | C7: Training | D7: Flex Trainer | E7: Xl | F7: 1 | G7: 3167.33 | H7: 0.53 | I7: 1488.65 | K7: Retail | L7: Pune | M7: 1567.37
A8: 2135 | B8: Men | C8: Basketball | D8: Zoom Freak | E8: L | F8: 2 | G8: 9106.61 | H8: 0.74 | I8: 4735.44 | J8: 45599 | K8: Retail | L8: Hyderabad | M8: 2422.38
A9: 2150 | B9: Women | C9: Basketball | D9: Lebron 20 | E9: M | F9: 2 | G9: 3313.21 | H9: 0.48 | I9: 3445.74 | J9: 45844 | K9: Online | L9: Bengaluru | M9: 3221.62
A10: 2169 | B10: Kids | C10: Training | D10: Flex Trainer | F10: 4 | G10: 4046.05 | H10: 0.01 | I10: 16022.36 | J10: 45640 | K10: Retail | L10: Delhi | M10: 1057.58
A11: 2185 | B11: Women | C11: Training | D11: Zoomx Invincible | E11: Xl | F11: 4 | G11: 4207.44 | H11: 0.59 | I11: 6900.2 | J11: 45816 | K11: Online | L11: Kolkata | M11: -615.48
A12: 2202 | B12: Men | C12: Basketball | D12: Kyrie Flytrap | E12: M | F12: -1 | G12: 7918.93 | H12: 1.06 | I12: 475.14 | J12: 45842 | K12: Retail | L12: Bengaluru | M12: 1994.42
A13: 2222 | B13: Men | C13: Training | D13: Zoomx Invincible | E13: Xl | F13: 2 | G13: 8897.19 | H13: 0.11 | I13: 15837 | J13: 45647 | K13: Retail | L13: Mumbai | M13: 2821.69
A14: 2248 | B14: Men | C14: Training | D14: Metcon 7 | E14: M | F14: 4 | G14: 8249.96 | H14: 0.24 | I14: 25079.88 | J14: 45307 | K14: Online | L14: Bengaluru | M14: 1625.14
A15: 2300 | B15: Men | C15: Basketball | D15: Air Jordan | E15: L | F15: 3 | G15: 6331.64 | H15: 0.78 | I15: 4178.88 | J15: 45521 | K15: Retail | L15: Delhi | M15: 3380.28
A16: 2306 | B16: Kids | C16: Basketball | D16: Air Jordan | F16: 1 | G16: 8267.56 | H16: 0.29 | I16: 5869.97 | J16: 45606 | K16: Retail | L16: Bengaluru | M16: 476.25
A17: 2328 | B17: Men | C17: Lifestyle | D17: Waffle One | E17: 6 | F17: 2 | G17: 6449.46 | H17: 0.29 | I17: 9158.23 | J17: 45605 | K17: Online | L17: Mumbai | M17: 39.69
A18: 2367 | B18: Kids | C18: Lifestyle | D18: Dunk Low | E18: Xl | F18: 4 | G18: 6202.99 | H18: 0.84 | I18: 3969.91 | J18: 45608 | K18: Online | L18: Bengaluru | M18: -202.12
A19: 2412 | B19: Kids | C19: Lifestyle | D19: Blazer Mid | E19: Xl | F19: 1 | G19: 4920.3 | H19: 0.14 | I19: 4231.46 | K19: Retail | L19: Mumbai | M19: 1135.72
A20: 2413 | B20: Men | C20: Training | D20: Flex Trainer | E20: Xl | F20: 3 | G20: 7005.67 | H20: 0.15 | I20: 17864.46 | K20: Retail | L20: Kolkata | M20: 2329.98
A21: 2432 | B21: Women | C21: Basketball | D21: Zoom Freak | E21: L | F21: 1 | G21: 3036.61 | H21: 0.86 | I21: 425.13 | J21: 45591 | K21: Online | L21: Mumbai | M21: 3754.3
A22: 2460 | B22: Women | C22: Basketball | D22: Zoom Freak | E22: Xl | F22: 2 | G22: 5482.96 | H22: 0.35 | I22: 7127.85 | J22: 45600 | K22: Online | L22: Kolkata | M22: -823.8
A23: 2481 | B23: Women | C23: Soccer | D23: Premier Iii | E23: 7 | F23: 1 | G23: 9145.37 | H23: 0.07 | I23: 8505.19 | J23: 45764 | K23: Online | L23: Pune | M23: 1755.19
A24: 2487 | B24: Men | C24: Running | D24: Air Zoom | E24: L | F24: 3 | G24: 5881.13 | H24: 0.8 | I24: 3528.68 | J24: 45747 | K24: Online | L24: Hyderabad | M24: 2108.4
A25: 2490 | B25: Women | C25: Soccer | D25: Premier Iii | E25: L | F25: 3 | G25: 5015.19 | H25: 0.75 | I25: 3761.39 | J25: 45622 | K25: Online | L25: Hyderabad | M25: -494.53
A26: 2496 | B26: Kids | C26: Running | D26: React Infinity | E26: M | F26: 2 | G26: 4110.72 | H26: 0.32 | I26: 5590.58 | J26: 45650 | K26: Retail | L26: Bengaluru | M26: 3894.95
A27: 2535 | B27: Men | C27: Soccer | D27: Tiempo Legend | E27: Xl | F27: 2 | G27: 2786.84 | H27: 0.21 | I27: 4403.21 | J27: 45682 | K27: Online | L27: Mumbai | M27: 3345.36
A28: 2550 | B28: Men | C28: Soccer | D28: Premier Iii | E28: Xl | F28: 1 | G28: 6121.21 | H28: 0.05 | I28: 5815.15 | J28: 45177 | K28: Online | L28: Kolkata | M28: 2470.08
A29: 2563 | B29: Men | C29: Soccer | D29: Mercurial Superfly | E29: M | F29: 2 | G29: 9443.35 | H29: 0.54 | I29: 8687.88 | J29: 45760 | K29: Retail | L29: Kolkata | M29: 2706.61
A30: 2569 | B30: Women | C30: Basketball | D30: Air Jordan | E30: L | F30: 2 | G30: 9605.11 | H30: 0.88 | I30: 2305.23 | J30: 45528 | K30: Online | L30: Hyderabad | M30: 128.89
A31: 2594 | B31: Women | C31: Training | D31: Zoomx Invincible | E31: Xl | F31: 3 | G31: 7944.34 | H31: 0.67 | I31: 7864.9 | J31: 45345 | K31: Retail | L31: Hyderabad | M31: 1534.91
A32: 2613 | B32: Women | C32: Lifestyle | D32: Waffle One | E32: 7 | F32: 3 | G32: 4374.83 | H32: 0.27 | I32: 9580.88 | K32: Retail | L32: Delhi | M32: 1473.37
A33: 2615 | B33: Women | C33: Soccer | D33: Phantom Gt | E33: Xl | F33: 3 | G33: 3042.37 | H33: 0.12 | I33: 8031.86 | J33: 45740 | K33: Online | L33: Pune | M33: 2105.48
A34: 2621 | B34: Kids | C34: Soccer | D34: Phantom Gt | E34: L | F34: 3 | G34: 6466.57 | H34: 0.59 | I34: 7953.88 | J34: 45431 | K34: Online | L34: Bengaluru | M34: -1152.86
A35: 2709 | B35: Kids | C35: Running | D35: Free Rn | E35: 10 | F35: 1 | G35: 6302.98 | H35: 0.48 | I35: 3277.55 | J35: 45724 | K35: Retail | L35: Delhi | M35: 2835.93
A36: 2713 | B36: Men | C36: Lifestyle | D36: Air Force 1 | E36: L | F36: 1 | G36: 7877.36 | H36: 0.55 | I36: 3544.81 | J36: 45787 | K36: Retail | L36: Kolkata | M36: 3663.49
A37: 2780 | B37: Men | C37: Training | D37: Metcon 7 | E37: 6 | F37: 1 | G37: 4308.75 | H37: 0.32 | I37: 2929.95 | K37: Online | L37: Hyderabad | M37: 799.35
A38: 2781 | B38: Men | C38: Training | D38: Metcon 7 | E38: 12 | F38: 1 | G38: 6546.59 | H38: 0.68 | I38: 2094.91 | J38: 45172 | K38: Retail | L38: Bengaluru | M38: 1504.31
A39: 2799 | B39: Kids | C39: Training | D39: Superrep Go | F39: 3 | G39: 2359.47 | H39: 0.54 | I39: 3256.07 | J39: 45846 | K39: Online | L39: Mumbai | M39: 3165.65
A40: 2810 | B40: Men | C40: Running | D40: Air Zoom | E40: 7 | F40: 2 | G40: 2943.44 | H40: 0.53 | I40: 2766.83 | K40: Retail | L40: Hyderabad | M40: 405.67
A41: 2812 | B41: Men | C41: Basketball | D41: Lebron 20 | F41: 2 | G41: 9507.39 | H41: 0.01 | I41: 18824.63 | J41: 45512 | K41: Online | L41: Kolkata | M41: 2570.01
A42: 2844 | B42: Men | C42: Lifestyle | D42: Waffle One | F42: 2 | G42: 6495.53 | H42: 0.23 | I42: 10003.12 | K42: Retail | L42: Mumbai | M42: -951.85
A43: 2904 | B43: Women | C43: Soccer | D43: Tiempo Legend | E43: 9 | F43: 2 | G43: 8644.67 | H43: 0.54 | I43: 7953.1 | J43: 45776 | K43: Online | L43: Bengaluru | M43: 2711.75
A44: 2912 | B44: Kids | C44: Running | D44: React Infinity | E44: Xl | F44: 2 | G44: 9839.63 | H44: 0.98 | I44: 393.59 | J44: 45358 | K44: Online | L44: Bengaluru | M44: 1218.22
A45: 2936 | B45: Women | C45: Training | D45: Flex Trainer | E45: Xl | F45: 1 | G45: 6496.58 | H45: 0.29 | I45: 4612.57 | J45: 45504 | K45: Retail | L45: Pune | M45: 1933.1
A46: 2942 | B46: Women | C46: Training | D46: Flex Trainer | E46: 10 | F46: 4 | G46: 5222.39 | H46: 0.57 | I46: 8982.51 | J46: 45763 | K46: Online | L46: Bengaluru | M46: -68.53
A47: 2977 | B47: Kids | C47: Training | D47: Zoomx Invincible | E47: 8 | F47: 3 | G47: 2959.26 | H47: 0.37 | I47: 5593 | K47: Online | L47: Kolkata | M47: -821.76
A48: 3030 | B48: Men | C48: Soccer | D48: Mercurial Superfly | F48: 3 | G48: 6969.28 | H48: 0.58 | I48: 8781.29 | J48: 45146 | K48: Online | L48: Kolkata | M48: 98.19
A49: 3047 | B49: Women | C49: Basketball | D49: Kyrie Flytrap | F49: 3 | G49: 6175.84 | H49: 0.9 | I49: 1852.75 | J49: 45579 | K49: Online | L49: Hyderabad | M49: -960.94
A50: 3062 | B50: Women | C50: Soccer | D50: Phantom Gt | F50: 1 | G50: 6936.34 | H50: 0.46 | I50: 3745.62 | J50: 45735 | K50: Retail | L50: Mumbai | M50: 1647.34
A51: 3091 | B51: Women | C51: Basketball | D51: Air Jordan | F51: 1 | G51: 8666.84 | H51: 0.3 | I51: 6066.79 | J51: 45701 | K51: Online | L51: Hyderabad | M51: 204.77
A52: 3127 | B52: Men | C52: Training | D52: Zoomx Invincible | E52: Xl | F52: 1 | G52: 4614.33 | H52: 0.47 | I52: 2445.59 | J52: 45572 | K52: Online | L52: Pune | M52: -440.44
A53: 3143 | B53: Men | C53: Training | D53: Flex Trainer | E53: 7 | F53: 3 | G53: 3938.59 | H53: 0.98 | I53: 236.32 | J53: 45527 | K53: Online | L53: Mumbai | M53: 635.39
A54: 3165 | B54: Women | C54: Soccer | D54: Phantom Gt | E54: Xl | F54: 2 | G54: 2530.29 | H54: 0.29 | I54: 3593.01 | J54: 45705 | K54: Online | L54: Kolkata | M54: 3264.03
A55: 3177 | B55: Kids | C55: Lifestyle | D55: Air Force 1 | E55: L | F55: 3 | G55: 7042.12 | H55: 0.89 | I55: 2323.9 | K55: Online | L55: Mumbai | M55: -411.55
A56: 3189 | B56: Men | C56: Basketball | D56: Lebron 20 | E56: L | F56: 3 | G56: 6730.48 | H56: 0.33 | I56: 13528.26 | J56: 45696 | K56: Online | L56: Kolkata | M56: 1456.87
A57: 3217 | B57: Men | C57: Soccer | D57: Tiempo Legend | E57: 6 | F57: 1 | G57: 4819.75 | H57: 0.22 | I57: 3759.41 | J57: 45703 | K57: Retail | L57: Pune | M57: -514.9
A58: 3221 | B58: Women | C58: Basketball | D58: Lebron 20 | F58: 2 | G58: 9682.68 | H58: 0.88 | I58: 2323.84 | J58: 45556 | K58: Online | L58: Pune | M58: 1650.44
A59: 3224 | B59: Women | C59: Soccer | D59: Phantom Gt | F59: 1 | G59: 9872.38 | H59: 0.18 | I59: 8095.35 | J59: 45734 | K59: Retail | L59: Pune | M59: 233.85
A60: 3238 | B60: Women | C60: Training | D60: Superrep Go | E60: Xl | F60: 1 | G60: 4420.21 | H60: 0.32 | I60: 3005.74 | K60: Retail | L60: Mumbai | M60: 705.58
A61: 3274 | B61: Men | C61: Training | D61: Superrep Go | E61: L | F61: 3 | G61: 6031.14 | H61: 0.15 | I61: 15379.41 | J61: 45780 | K61: Retail | L61: Hyderabad | M61: 169.05
A62: 3279 | B62: Kids | C62: Soccer | D62: Mercurial Superfly | E62: Xl | F62: 4 | G62: 2572.41 | H62: 0.1 | I62: 9260.68 | J62: 45605 | K62: Retail | L62: Delhi | M62: 3098.28
A63: 3357 | B63: Kids | C63: Training | D63: Flex Trainer | E63: M | F63: 4 | G63: 6206.45 | H63: 0.5 | I63: 12412.9 | J63: 45752 | K63: Online | L63: Delhi | M63: 678.42
A64: 3379 | B64: Men | C64: Basketball | D64: Air Jordan | F64: 2 | G64: 5000.49 | H64: 0.86 | I64: 1400.14 | J64: 45588 | K64: Retail | L64: Pune | M64: 3000.14
A65: 3409 | B65: Kids | C65: Running | D65: Air Zoom | E65: M | F65: 1 | G65: 6312.01 | H65: 0.3 | I65: 4418.41 | J65: 45543 | K65: Retail | L65: Delhi | M65: -1106.07
A66: 3428 | B66: Women | C66: Basketball | D66: Air Jordan | E66: 6 | F66: 1 | G66: 2825.86 | H66: 0.23 | I66: 2175.91 | J66: 45629 | K66: Online | L66: Bengaluru | M66: 625.3
A67: 3466 | B67: Men | C67: Basketball | D67: Kyrie Flytrap | F67: 2 | G67: 6498.22 | H67: 0.5 | I67: 6498.22 | J67: 45589 | K67: Retail | L67: Mumbai | M67: -360.53
A68: 3468 | B68: Men | C68: Soccer | D68: Phantom Gt | F68: 4 | G68: 9577.99 | H68: 0.93 | I68: 2681.84 | K68: Online | L68: Kolkata | M68: -259.93
A69: 3534 | B69: Kids | C69: Basketball | D69: Zoom Freak | F69: 3 | G69: 3280.57 | H69: 0.62 | I69: 3739.85 | J69: 45605 | K69: Retail | L69: Kolkata | M69: 427.76
A70: 3573 | B70: Men | C70: Basketball | D70: Air Jordan | F70: 1 | G70: 6830.98 | H70: 0.39 | I70: 4166.9 | J70: 45734 | K70: Retail | L70: Mumbai | M70: -175.76
A71: 3662 | B71: Kids | C71: Lifestyle | D71: Waffle One | F71: 4 | G71: 9032.9 | H71: 0.64 | I71: 13007.38 | K71: Online | L71: Bengaluru | M71: 131.76
A72: 3667 | B72: Kids | C72: Running | D72: Air Zoom | E72: M | F72: 4 | G72: 9386.2 | H72: 0.01 | I72: 37169.35 | K72: Online | L72: Pune | M72: -1121.02
A73: 3672 | B73: Women | C73: Soccer | D73: Tiempo Legend | E73: 7 | F73: 3 | G73: 7127.18 | H73: 0.32 | I73: 14539.45 | J73: 45520 | K73: Online | L73: Delhi | M73: 2651.63
A74: 3680 | B74: Men | C74: Training | D74: Flex Trainer | E74: Xl | F74: 3 | G74: 8835.41 | H74: 0.92 | I74: 2120.5 | J74: 45684 | K74: Retail | L74: Delhi | M74: -746.28
A75: 3719 | B75: Men | C75: Running | D75: Free Rn | F75: 2 | G75: 5943.38 | H75: 0.23 | I75: 9152.81 | J75: 45829 | K75: Online | L75: Bengaluru | M75: 3260.51
A76: 3722 | B76: Kids | C76: Training | D76: Zoomx Invincible | E76: 7 | F76: 1 | G76: 9335 | H76: 0.22 | I76: 7281.3 | J76: 45251 | K76: Retail | L76: Mumbai | M76: 1787.45
A77: 3738 | B77: Men | C77: Soccer | D77: Premier Iii | E77: 11 | F77: 1 | G77: 6968.08 | H77: 0.02 | I77: 6828.72 | J77: 45746 | K77: Online | L77: Delhi | M77: -673.94
A78: 3741 | B78: Kids | C78: Lifestyle | D78: Air Force 1 | E78: L | F78: 2 | G78: 8927.22 | H78: 0.2 | I78: 14283.55 | J78: 45851 | K78: Retail | L78: Kolkata | M78: 821.32
A79: 3755 | B79: Women | C79: Soccer | D79: Phantom Gt | E79: 8 | F79: 4 | G79: 2342.16 | H79: 0.25 | I79: 7026.48 | J79: 45767 | K79: Retail | L79: Mumbai | M79: 1007
A80: 3761 | B80: Women | C80: Basketball | D80: Zoom Freak | E80: L | F80: 4 | G80: 2972.38 | H80: 0.14 | I80: 10224.99 | J80: 45614 | K80: Online | L80: Hyderabad | M80: 2569.74
A81: 3785 | B81: Kids | C81: Lifestyle | D81: Blazer Mid | E81: Xl | F81: 3 | G81: 6464 | H81: 0.45 | I81: 10665.6 | K81: Retail | L81: Delhi | M81: 698.11
A82: 3796 | B82: Women | C82: Basketball | D82: Zoom Freak | F82: 4 | G82: 6165.64 | H82: 0.16 | I82: 20716.55 | J82: 45648 | K82: Online | L82: Delhi | M82: 2081.43
A83: 3874 | B83: Women | C83: Basketball | D83: Lebron 20 | E83: Xl | F83: 4 | G83: 3305.6 | H83: 0.7 | I83: 3966.72 | J83: 45531 | K83: Online | L83: Kolkata | M83: 1605.13
A84: 3881 | B84: Women | C84: Training | D84: Superrep Go | F84: 3 | G84: 3656.98 | H84: 0.06 | I84: 10312.68 | K84: Online | L84: Hyderabad | M84: 1953.91
A85: 3894 | B85: Women | C85: Soccer | D85: Premier Iii | E85: 11 | F85: -1 | G85: 5255.98 | H85: 1.03 | I85: 157.68 | J85: 45451 | K85: Online | L85: Pune | M85: -1067.96
A86: 3897 | B86: Women | C86: Soccer | D86: Tiempo Legend | E86: 8 | F86: 2 | G86: 6050.27 | H86: 0.69 | I86: 3751.17 | K86: Retail | L86: Delhi | M86: 3332.49
A87: 3906 | B87: Men | C87: Lifestyle | D87: Dunk Low | E87: Xl | F87: 4 | G87: 7588.77 | H87: 0.14 | I87: 26105.37 | J87: 45539 | K87: Online | L87: Hyderabad | M87: 3435.73
A88: 3928 | B88: Men | C88: Running | D88: Pegasus Turbo | F88: 2 | G88: 5636.21 | H88: 0.74 | I88: 2930.83 | K88: Retail | L88: Delhi | M88: -984.86
A89: 3929 | B89: Kids | C89: Running | D89: Free Rn | F89: 1 | G89: 4199.97 | H89: 0.9 | I89: 420 | J89: 45791 | K89: Retail | L89: Mumbai | M89: -861.44
A90: 3932 | B90: Kids | C90: Training | D90: Superrep Go | E90: L | F90: 4 | G90: 4520.97 | H90: 0.54 | I90: 8318.58 | J90: 45818 | K90: Retail | L90: Bengaluru | M90: 1289.36
A91: 3988 | B91: Kids | C91: Lifestyle | D91: Blazer Mid | E91: M | F91: 4 | G91: 7945.46 | H91: 0.67 | I91: 10488.01 | J91: 45575 | K91: Online | L91: Pune | M91: 3698.62
A92: 4008 | B92: Men | C92: Basketball | D92: Lebron 20 | E92: 9 | F92: 3 | G92: 7737.27 | H92: 0.07 | I92: 21586.98 | J92: 45275 | K92: Retail | L92: Hyderabad | M92: 180.31
A93: 4031 | B93: Men | C93: Soccer | D93: Phantom Gt | F93: 2 | G93: 4272.26 | H93: 0.83 | I93: 1452.57 | K93: Retail | L93: Kolkata | M93: 1977.91
A94: 4033 | B94: Men | C94: Lifestyle | D94: Blazer Mid | E94: L | F94: 4 | G94: 4398.68 | H94: 0.27 | I94: 12844.15 | K94: Retail | L94: Bengaluru | M94: 3573.92
A95: 4043 | B95: Kids | C95: Running | D95: Air Zoom | F95: 4 | G95: 5235.22 | H95: 0.51 | I95: 10261.03 | J95: 45805 | K95: Online | L95: Hyderabad | M95: 3321.49
A96: 4066 | B96: Kids | C96: Running | D96: React Infinity | E96: L | F96: 4 | G96: 6599.26 | H96: 0.85 | I96: 3959.56 | J96: 45837 | K96: Retail | L96: Bengaluru | M96: 3344.47
A97: 4088 | B97: Men | C97: Training | D97: Flex Trainer | E97: M | F97: 2 | G97: 5649.73 | H97: 0.41 | I97: 6666.68 | J97: 45732 | K97: Retail | L97: Mumbai | M97: 1548.1
A98: 4108 | B98: Kids | C98: Running | D98: Pegasus Turbo | E98: L | F98: 2 | G98: 2767.55 | H98: 0.19 | I98: 4483.43 | J98: 45255 | K98: Online | L98: Kolkata | M98: 1059.07
A99: 4220 | B99: Kids | C99: Lifestyle | D99: Dunk Low | E99: M | F99: 2 | G99: 2290.64 | H99: 0.84 | I99: 733 | J99: 45688 | K99: Retail | L99: Delhi | M99: 608.16
A100: 4249 | B100: Kids | C100: Training | D100: Flex Trainer | E100: L | F100: 1 | G100: 2902.95 | H100: 0.6 | I100: 1161.18 | J100: 45576 | K100: Retail | L100: Bengaluru | M100: -855.08
...

Sheet Sheet2
A9: Sum of Revenue | B9: Column Labels | I9: Row Labels | J9: Sum of Revenue
A10: Row Labels | B10: Basketball | C10: Lifestyle | D10: Running | E10: Soccer | F10: Training | G10: Grand Total | I10: Air Force 1 | J10: 42612.14 | L10: Row Labels | M10: Sum of Revenue
A11: Kids | B11: 14140.52 | C11: 71713.02 | D11: 69973.5 | E11: 17214.56 | F11: 54045.39 | G11: 227086.99 | I11: Air Jordan | J11: 44854.03 | L11: Bengaluru | M11: 127441.95
A12: Online | B12: 4530.7 | C12: 29789.2 | D12: 52307.4 | E12: 7953.88 | F12: 21261.97 | G12: 115843.15 | I12: Air Zoom | J12: 58144.3 | L12: Delhi | M12: 123952.47
A13: Retail | B13: 9609.82 | C13: 41923.82 | D13: 17666.1 | E13: 9260.68 | F13: 32783.42 | G13: 111243.84 | I13: Blazer Mid | J13: 50239.43 | L13: Hyderabad | M13: 140181.79
A14: Men | B14: 79580.5 | C14: 61655.68 | D14: 18379.15 | E14: 59901.91 | F14: 91137.17 | G14: 310654.41 | I14: Flex Trainer | J14: 77067.95 | L14: Kolkata | M14: 165502.6
A15: Online | B15: 32352.89 | C15: 35263.6 | D15: 12681.49 | E15: 31025.2 | F15: 30691.74 | G15: 142014.92 | I15: Lebron 20 | J15: 63676.17 | L15: Mumbai | M15: 106244.5
A16: Retail | B16: 47227.61 | C16: 26392.08 | D16: 5697.66 | E16: 28876.71 | F16: 60445.43 | G16: 168639.49 | I16: Phantom Gt | J16: 42580.61 | L16: Pune | M16: 123655.54
A17: Women | B17: 75732.56 | C17: 32040.76 | D17: 6257.1 | E17: 69160.3 | F17: 66046.73 | G17: 249237.45 | I17: Superrep Go | J17: 49055.58 | L17: Grand Total | M17: 786978.85
A18: Online | B18: 60631.5 | E18: 46541.68 | F18: 35086.33 | G18: 142259.51 | I18: Zoom Freak | J18: 51500.51
A19: Retail | B19: 15101.06 | C19: 32040.76 | D19: 6257.1 | E19: 22618.62 | F19: 30960.4 | G19: 106977.94 | I19: Zoomx Invincible | J19: 46404.46
A20: Grand Total | B20: 169453.58 | C20: 165409.46 | D20: 94609.75 | E20: 146276.77 | F20: 211229.29 | G20: 786978.85 | I20: Grand Total | J20: 526135.18

Sheet Sheet3
D3: Product_name | E3: =Sheet2!J9 -> Sum of Revenue
D4: =Sheet2!I10 -> Air Force 1 | E4: =Sheet2!J10 -> 42612.14
D5: =Sheet2!I11 -> Air Jordan | E5: =Sheet2!J11 -> 44854.03
D6: =Sheet2!I12 -> Air Zoom | E6: =Sheet2!J12 -> 58144.3
D7: =Sheet2!I13 -> Blazer Mid | E7: =Sheet2!J13 -> 50239.43
D8: =Sheet2!I14 -> Flex Trainer | E8: =Sheet2!J14 -> 77067.95
D9: =Sheet2!I15 -> Lebron 20 | E9: =Sheet2!J15 -> 63676.17
D10: =Sheet2!I16 -> Phantom Gt | E10: =Sheet2!J16 -> 42580.61
D11: =Sheet2!I17 -> Superrep Go | E11: =Sheet2!J17 -> 49055.58
D12: =Sheet2!I18 -> Zoom Freak | E12: =Sheet2!J18 -> 51500.51
D13: =Sheet2!I19 -> Zoomx Invincible | E13: =Sheet2!J19 -> 46404.46
D14: =Sheet2!I20 -> Grand Total | E14: =Sheet2!J20 -> 526135.18
